LICENSE
MANIFEST.in
README.md
setup.cfg
setup.py
versioneer.py
./.gitattributes
./CODE_OF_CONDUCT.md
./CONTRIBUTING.md
./LICENSE
./MANIFEST.in
./README.md
./setup.cfg
./setup.py
./versioneer.py
./adclean/__init__.py
./adclean/_version.py
./adclean/cleaner.py
./adclean.egg-info/PKG-INFO
./adclean.egg-info/SOURCES.txt
./adclean.egg-info/dependency_links.txt
./adclean.egg-info/requires.txt
./adclean.egg-info/top_level.txt
./tests/__init__.py
./tests/conftest.py
./tests/test_adclean.py
adclean/__init__.py
adclean/_version.py
adclean/cleaner.py
adclean.egg-info/PKG-INFO
adclean.egg-info/SOURCES.txt
adclean.egg-info/dependency_links.txt
adclean.egg-info/requires.txt
adclean.egg-info/top_level.txt
tests/__init__.py
tests/conftest.py
tests/test_adclean.py